oscillators/__init__.py
oscillators/__main__.py
oscillators/calibration.py
oscillators/core.py
oscillators/examples.py
oscillators/logging_config.py
oscillators/models.py
oscillators/py.typed
oscillators/simulation.py
oscillators/visualization.py
oscillators_cosmology-0.2.0.dist-info/METADATA
oscillators_cosmology-0.2.0.dist-info/WHEEL
oscillators_cosmology-0.2.0.dist-info/entry_points.txt
oscillators_cosmology-0.2.0.dist-info/top_level.txt
oscillators_cosmology-0.2.0.dist-info/RECORD
