Metadata-Version: 2.4
Name: oscillators-cosmology
Version: 0.2.0
Summary: Библиотека для моделирования рождения материи во Вселенной
Author-email: Timur Isanov <xtimon@yahoo.com>
Maintainer-email: Timur Isanov <xtimon@yahoo.com>
License: MIT
Project-URL: Homepage, https://github.com/xtimon/oscillator
Project-URL: Documentation, https://github.com/xtimon/oscillator#readme
Project-URL: Repository, https://github.com/xtimon/oscillator
Project-URL: Issues, https://github.com/xtimon/oscillator/issues
Project-URL: Changelog, https://github.com/xtimon/oscillator/releases
Keywords: cosmology,physics,simulation,matter,universe,inflation,leptogenesis,parametric-resonance,big-bang,particle-physics
Classifier: Development Status :: 3 - Alpha
Classifier: Intended Audience :: Science/Research
Classifier: License :: OSI Approved :: MIT License
Classifier: Operating System :: OS Independent
Classifier: Programming Language :: Python :: 3
Classifier: Programming Language :: Python :: 3.9
Classifier: Programming Language :: Python :: 3.10
Classifier: Programming Language :: Python :: 3.11
Classifier: Programming Language :: Python :: 3.12
Classifier: Programming Language :: Python :: 3.13
Classifier: Topic :: Scientific/Engineering :: Physics
Classifier: Topic :: Scientific/Engineering :: Astronomy
Classifier: Typing :: Typed
Requires-Python: >=3.9
Requires-Dist: numpy>=1.20.0
Requires-Dist: scipy>=1.7.0
Requires-Dist: matplotlib>=3.4.0
Requires-Dist: tqdm>=4.60.0
Requires-Dist: mpmath>=1.2.0
Provides-Extra: dev
Requires-Dist: pytest>=7.0.0; extra == "dev"
Requires-Dist: pytest-cov>=4.0.0; extra == "dev"
Requires-Dist: black>=23.0.0; extra == "dev"
Requires-Dist: flake8>=6.0.0; extra == "dev"
Requires-Dist: mypy>=1.0.0; extra == "dev"
Requires-Dist: ruff>=0.1.0; extra == "dev"
Provides-Extra: cli
Requires-Dist: click>=8.0.0; extra == "cli"
Provides-Extra: gpu
Requires-Dist: mlx>=0.1.0; (sys_platform == "darwin" and platform_machine == "arm64") and extra == "gpu"
Provides-Extra: docs
Requires-Dist: sphinx>=6.0.0; extra == "docs"
Requires-Dist: sphinx-rtd-theme>=1.0.0; extra == "docs"
Requires-Dist: myst-parser>=1.0.0; extra == "docs"
Provides-Extra: all
Requires-Dist: oscillators-cosmology[cli,dev,docs]; extra == "all"
